my_own_package/__init__.py
flo_project-0.1.0.dist-info/METADATA
flo_project-0.1.0.dist-info/WHEEL
flo_project-0.1.0.dist-info/top_level.txt
flo_project-0.1.0.dist-info/RECORD
