Metadata-Version: 2.1
Name: flo-project
Version: 0.1.0
Summary: say hello
Author: flo
Author-email: tore2flo@yahoo.com
License: UNKNOWN
Platform: UNKNOWN
